oca/cluster.py
oca/datastore.py
oca/group.py
oca/template.py
oca/vn.py
oca/pool.py
oca/vm.py
oca/__init__.py
oca/user.py
oca/host.py
oca/image.py
oca/exceptions.py
oca/acl.py
oca-4.10.0_a1.dist-info/METADATA
oca-4.10.0_a1.dist-info/DESCRIPTION.rst
oca-4.10.0_a1.dist-info/metadata.json
oca-4.10.0_a1.dist-info/top_level.txt
oca-4.10.0_a1.dist-info/WHEEL
oca-4.10.0_a1.dist-info/RECORD
