Metadata-Version: 2.0
Name: oca
Version: 4.10.0-a1
Summary: Python Bindings for XMLRPC OpenNebula Cloud API
Home-page: https://github.com/python-oca/python-oca
Author: Łukasz Oleś, Matthias Schmitz, Michael Schmidt
Author-email: UNKNOWN
License: Apache License 2.0
Keywords: opennebula cloud xmlrpc
Platform: UNKNOWN
Classifier: Development Status :: 3 - Alpha
Classifier: License :: OSI Approved :: Apache Software License
Classifier: License :: OSI Approved :: Apache Software License
Classifier: Operating System :: OS Independent
